withopen/__init__.py
withopen/archive.py
withopen/main.py
withopen/mdb_ScreenBuffer.py
withopen/mdb_control_file_visibility.py
withopen/mdb_core.py
withopen/mdb_date_change.py
withopen/mdb_future_datetime.py
withopen/mdb_how_long.py
withopen/mdb_loop_progress.py
withopen/mdb_max_clear.py
withopen/mdb_mini_guide.py
withopen/mdb_others.py
withopen/mdb_pretty_print.py
withopen/mdb_session_id_generator.py
withopen/mdb_validations.py
withopen/mdb_wait_queue.py
withopen-6.5.1.dist-info/METADATA
withopen-6.5.1.dist-info/WHEEL
withopen-6.5.1.dist-info/top_level.txt
withopen-6.5.1.dist-info/RECORD
