Metadata-Version: 2.4
Name: withopen
Version: 6.5.1
Summary: A structured and backup-friendly way to manage `.txt` files with multi-console and debugging support.
Author: henry
Author-email: osas2henry@gmail.com
Classifier: Programming Language :: Python :: 3
Classifier: Operating System :: OS Independent
Classifier: License :: OSI Approved :: MIT License
Requires-Python: >=3.7
Dynamic: author
Dynamic: author-email
Dynamic: classifier
Dynamic: description
Dynamic: description-content-type
Dynamic: requires-python
Dynamic: summary
